{
  "created_at": "Wed Jun 20 01:54:44 +0000 2012",
  "id": 215261367815516161,
  "id_str": "215261367815516161",
  "text": "America's impending #edu showdown: \"business vs. academia.\" Is #UVA debate a harbinger of things to come?",
  "source": "web",
  "truncated": false,
  "in_reply_to_status_id": null,
  "in_reply_to_status_id_str": null,
  "in_reply_to_user_id": null,
  "in_reply_to_user_id_str": null,
  "in_reply_to_screen_name": null,
  "user": {
    "id": 19717941,
    "id_str": "19717941",
    "name": "Kathy Moore",
    "screen_name": "kathy_moore",
    "location": "Staunton, Virginia",
    "description": "Public relations, marketing and branding strategist - focusing on tourism, vibrant downtowns, placemaking, location marketing, design and economic development.",
    "url": "http://www.moorepublicrelations.com",
    "entities": {
      "url": {
        "urls": [
          {
            "url": "http://www.moorepublicrelations.com",
            "expanded_url": null,
            "indices": [
              0,
              35
            ]
          }
        ]
      },
      "description": {
        "urls": [

        ]
      }
    },
    "protected": false,
    "followers_count": 2690,
    "friends_count": 2024,
    "listed_count": 130,
    "created_at": "Thu Jan 29 16:19:03 +0000 2009",
    "favourites_count": 186,
    "utc_offset": -18000,
    "time_zone": "Eastern Time (US & Canada)",
    "geo_enabled": false,
    "verified": false,
    "statuses_count": 4269,
    "lang": "en",
    "contributors_enabled": false,
    "is_translator": false,
    "profile_background_color": "E8E8E8",
    "profile_background_image_url": "http://a0.twimg.com/profile_background_images/223535986/kathy_moore_41856_twitbacks.jpg",
    "profile_background_image_url_https": "https://si0.twimg.com/profile_background_images/223535986/kathy_moore_41856_twitbacks.jpg",
    "profile_background_tile": false,
    "profile_image_url": "http://a0.twimg.com/profile_images/254488676/km_normal.jpg",
    "profile_image_url_https": "https://si0.twimg.com/profile_images/254488676/km_normal.jpg",
    "profile_banner_url": "https://si0.twimg.com/profile_banners/19717941/1358347947",
    "profile_link_color": "B51B4E",
    "profile_sidebar_border_color": "D7E0E3",
    "profile_sidebar_fill_color": "C6CACC",
    "profile_text_color": "333333",
    "profile_use_background_image": false,
    "default_profile": false,
    "default_profile_image": false,
    "following": false,
    "follow_request_sent": false,
    "notifications": false
  },
  "geo": null,
  "coordinates": null,
  "place": null,
  "contributors": null,
  "retweet_count": 0,
  "entities": {
    "hashtags": [
      {
        "text": "edu",
        "indices": [
          20,
          24
        ]
      },
      {
        "text": "UVA",
        "indices": [
          63,
          67
        ]
      }
    ],
    "urls": [

    ],
    "user_mentions": [

    ]
  },
  "favorited": false,
  "retweeted": false
}