{
  "created_at": "Sat Jun 23 00:50:53 +0000 2012",
  "id": 216332465181175808,
  "id_str": "216332465181175808",
  "text": "RT @Wahoos247: Attention #Virginia fans -- We're honoring subs to other #UVa sites to try our site for FREE! http://t.co/4PxxNWzZ #Wahoo ...",
  "source": "web",
  "truncated": false,
  "in_reply_to_status_id": null,
  "in_reply_to_status_id_str": null,
  "in_reply_to_user_id": null,
  "in_reply_to_user_id_str": null,
  "in_reply_to_screen_name": null,
  "user": {
    "id": 491028943,
    "id_str": "491028943",
    "name": "Jay Jenkins",
    "screen_name": "JayJenkins247",
    "location": "",
    "description": "Bringing baseball and beyond to the 247Sports platform. ",
    "url": null,
    "entities": {
      "description": {
        "urls": [

        ]
      }
    },
    "protected": false,
    "followers_count": 214,
    "friends_count": 182,
    "listed_count": 4,
    "created_at": "Mon Feb 13 05:23:28 +0000 2012",
    "favourites_count": 1,
    "utc_offset": null,
    "time_zone": null,
    "geo_enabled": false,
    "verified": false,
    "statuses_count": 484,
    "lang": "en",
    "contributors_enabled": false,
    "is_translator": false,
    "profile_background_color": "C0DEED",
    "profile_background_image_url": "http://a0.twimg.com/images/themes/theme1/bg.png",
    "profile_background_image_url_https": "https://si0.twimg.com/images/themes/theme1/bg.png",
    "profile_background_tile": false,
    "profile_image_url": "http://a0.twimg.com/profile_images/1837710821/Jay_in_press_box_normal.jpg",
    "profile_image_url_https": "https://si0.twimg.com/profile_images/1837710821/Jay_in_press_box_normal.jpg",
    "profile_link_color": "0084B4",
    "profile_sidebar_border_color": "C0DEED",
    "profile_sidebar_fill_color": "DDEEF6",
    "profile_text_color": "333333",
    "profile_use_background_image": true,
    "default_profile": true,
    "default_profile_image": false,
    "following": false,
    "follow_request_sent": false,
    "notifications": false
  },
  "geo": null,
  "coordinates": null,
  "place": null,
  "contributors": null,
  "retweeted_status": {
    "created_at": "Fri Jun 22 18:35:12 +0000 2012",
    "id": 216237920900747264,
    "id_str": "216237920900747264",
    "text": "Attention #Virginia fans -- We're honoring subs to other #UVa sites to try our site for FREE! http://t.co/4PxxNWzZ #Wahoos #Hoos #Cavaliers",
    "source": "<a href=\"http://www.tweetdeck.com\" rel=\"nofollow\">TweetDeck</a>",
    "truncated": false,
    "in_reply_to_status_id": null,
    "in_reply_to_status_id_str": null,
    "in_reply_to_user_id": null,
    "in_reply_to_user_id_str": null,
    "in_reply_to_screen_name": null,
    "user": {
      "id": 111583654,
      "id_str": "111583654",
      "name": "Wahoos247",
      "screen_name": "Wahoos247",
      "location": "",
      "description": "The new destination for Virginia Cavaliers football,  basketball news and recruiting scoop!  Proud member of the 247Sports network.",
      "url": "http://virginia.247sports.com/",
      "entities": {
        "url": {
          "urls": [
            {
              "url": "http://virginia.247sports.com/",
              "expanded_url": null,
              "indices": [
                0,
                30
              ]
            }
          ]
        },
        "description": {
          "urls": [

          ]
        }
      },
      "protected": false,
      "followers_count": 2003,
      "friends_count": 575,
      "listed_count": 76,
      "created_at": "Fri Feb 05 12:48:23 +0000 2010",
      "favourites_count": 1,
      "utc_offset": -18000,
      "time_zone": "Eastern Time (US & Canada)",
      "geo_enabled": false,
      "verified": false,
      "statuses_count": 10696,
      "lang": "en",
      "contributors_enabled": false,
      "is_translator": false,
      "profile_background_color": "FF5F03",
      "profile_background_image_url": "http://a0.twimg.com/profile_background_images/134462002/Grass.jpg",
      "profile_background_image_url_https": "https://si0.twimg.com/profile_background_images/134462002/Grass.jpg",
      "profile_background_tile": false,
      "profile_image_url": "http://a0.twimg.com/profile_images/1102236570/Wahoos247_logo_normal.jpg",
      "profile_image_url_https": "https://si0.twimg.com/profile_images/1102236570/Wahoos247_logo_normal.jpg",
      "profile_link_color": "FF5F03",
      "profile_sidebar_border_color": "FF5F03",
      "profile_sidebar_fill_color": "030029",
      "profile_text_color": "666666",
      "profile_use_background_image": true,
      "default_profile": false,
      "default_profile_image": false,
      "following": false,
      "follow_request_sent": false,
      "notifications": false
    },
    "geo": null,
    "coordinates": null,
    "place": null,
    "contributors": null,
    "retweet_count": 1,
    "entities": {
      "hashtags": [
        {
          "text": "Virginia",
          "indices": [
            10,
            19
          ]
        },
        {
          "text": "UVa",
          "indices": [
            57,
            61
          ]
        },
        {
          "text": "Wahoos",
          "indices": [
            115,
            122
          ]
        },
        {
          "text": "Hoos",
          "indices": [
            123,
            128
          ]
        },
        {
          "text": "Cavaliers",
          "indices": [
            129,
            139
          ]
        }
      ],
      "urls": [
        {
          "url": "http://t.co/4PxxNWzZ",
          "expanded_url": "http://bit.ly/JYr79X",
          "display_url": "bit.ly/JYr79X",
          "indices": [
            94,
            114
          ]
        }
      ],
      "user_mentions": [

      ]
    },
    "favorited": false,
    "retweeted": false,
    "possibly_sensitive": false
  },
  "retweet_count": 1,
  "entities": {
    "hashtags": [
      {
        "text": "Virginia",
        "indices": [
          25,
          34
        ]
      },
      {
        "text": "UVa",
        "indices": [
          72,
          76
        ]
      },
      {
        "text": "Wahoo",
        "indices": [
          130,
          136
        ]
      }
    ],
    "urls": [
      {
        "url": "http://t.co/4PxxNWzZ",
        "expanded_url": "http://bit.ly/JYr79X",
        "display_url": "bit.ly/JYr79X",
        "indices": [
          109,
          129
        ]
      }
    ],
    "user_mentions": [
      {
        "screen_name": "Wahoos247",
        "name": "Wahoos247",
        "id": 111583654,
        "id_str": "111583654",
        "indices": [
          3,
          13
        ]
      }
    ]
  },
  "favorited": false,
  "retweeted": false,
  "possibly_sensitive": false
}