{
  "created_at": "Sun Jun 24 07:21:31 +0000 2012",
  "id": 216793157780774912,
  "id_str": "216793157780774912",
  "text": "RT @johnruscher: Excellent piece on #UVA #Sullivan fiasco by @zachdcarter &amp; @dceiver - lead story on @HuffingtonPost right now! http ...",
  "source": "web",
  "truncated": false,
  "in_reply_to_status_id": null,
  "in_reply_to_status_id_str": null,
  "in_reply_to_user_id": null,
  "in_reply_to_user_id_str": null,
  "in_reply_to_screen_name": null,
  "user": {
    "id": 607306874,
    "id_str": "607306874",
    "name": "Amber",
    "screen_name": "amberopolis",
    "location": "DC ",
    "description": "public policy analyst, opinionated art critic, book lover, up/re-cycler, loves burritos, drinks coffee, travels with a french press.",
    "url": null,
    "entities": {
      "description": {
        "urls": [

        ]
      }
    },
    "protected": false,
    "followers_count": 14,
    "friends_count": 70,
    "listed_count": 0,
    "created_at": "Wed Jun 13 15:34:07 +0000 2012",
    "favourites_count": 0,
    "utc_offset": -14400,
    "time_zone": "Atlantic Time (Canada)",
    "geo_enabled": false,
    "verified": false,
    "statuses_count": 179,
    "lang": "en",
    "contributors_enabled": false,
    "is_translator": false,
    "profile_background_color": "B2DFDA",
    "profile_background_image_url": "http://a0.twimg.com/images/themes/theme13/bg.gif",
    "profile_background_image_url_https": "https://si0.twimg.com/images/themes/theme13/bg.gif",
    "profile_background_tile": false,
    "profile_image_url": "http://a0.twimg.com/profile_images/2331814610/izx7dy291agy8suqu946_normal.jpeg",
    "profile_image_url_https": "https://si0.twimg.com/profile_images/2331814610/izx7dy291agy8suqu946_normal.jpeg",
    "profile_link_color": "93A644",
    "profile_sidebar_border_color": "EEEEEE",
    "profile_sidebar_fill_color": "FFFFFF",
    "profile_text_color": "333333",
    "profile_use_background_image": true,
    "default_profile": false,
    "default_profile_image": false,
    "following": false,
    "follow_request_sent": false,
    "notifications": false
  },
  "geo": null,
  "coordinates": null,
  "place": null,
  "contributors": null,
  "retweeted_status": {
    "created_at": "Sun Jun 24 07:03:16 +0000 2012",
    "id": 216788566511075328,
    "id_str": "216788566511075328",
    "text": "Excellent piece on #UVA #Sullivan fiasco by @zachdcarter &amp; @dceiver - lead story on @HuffingtonPost right now! http://t.co/EbAdokBB",
    "source": "web",
    "truncated": false,
    "in_reply_to_status_id": null,
    "in_reply_to_status_id_str": null,
    "in_reply_to_user_id": null,
    "in_reply_to_user_id_str": null,
    "in_reply_to_screen_name": null,
    "user": {
      "id": 16024313,
      "id_str": "16024313",
      "name": "John Ruscher",
      "screen_name": "johnruscher",
      "location": "Brooklyn, NY",
      "description": "Writer. Editor at @EardrumNYC. New finds and old dreams. Everything's starting now.",
      "url": "http://t.co/Uh3BiZor",
      "entities": {
        "url": {
          "urls": [
            {
              "url": "http://t.co/Uh3BiZor",
              "expanded_url": "http://jrus.ch",
              "display_url": "jrus.ch",
              "indices": [
                0,
                20
              ]
            }
          ]
        },
        "description": {
          "urls": [

          ]
        }
      },
      "protected": false,
      "followers_count": 371,
      "friends_count": 620,
      "listed_count": 6,
      "created_at": "Thu Aug 28 07:16:46 +0000 2008",
      "favourites_count": 47,
      "utc_offset": -18000,
      "time_zone": "Quito",
      "geo_enabled": false,
      "verified": false,
      "statuses_count": 1337,
      "lang": "en",
      "contributors_enabled": false,
      "is_translator": false,
      "profile_background_color": "9AE4E8",
      "profile_background_image_url": "http://a0.twimg.com/profile_background_images/10999571/P1100107.JPG",
      "profile_background_image_url_https": "https://si0.twimg.com/profile_background_images/10999571/P1100107.JPG",
      "profile_background_tile": true,
      "profile_image_url": "http://a0.twimg.com/profile_images/2628626209/e465c4be43e96ffb5d13745c135486af_normal.png",
      "profile_image_url_https": "https://si0.twimg.com/profile_images/2628626209/e465c4be43e96ffb5d13745c135486af_normal.png",
      "profile_banner_url": "https://si0.twimg.com/profile_banners/16024313/1348100424",
      "profile_link_color": "8B0405",
      "profile_sidebar_border_color": "FFFFFF",
      "profile_sidebar_fill_color": "B8B8B8",
      "profile_text_color": "090E2F",
      "profile_use_background_image": true,
      "default_profile": false,
      "default_profile_image": false,
      "following": false,
      "follow_request_sent": false,
      "notifications": false
    },
    "geo": null,
    "coordinates": null,
    "place": null,
    "contributors": null,
    "retweet_count": 1,
    "entities": {
      "hashtags": [
        {
          "text": "UVA",
          "indices": [
            19,
            23
          ]
        },
        {
          "text": "Sullivan",
          "indices": [
            24,
            33
          ]
        }
      ],
      "urls": [
        {
          "url": "http://t.co/EbAdokBB",
          "expanded_url": "http://www.huffingtonpost.com/2012/06/24/uva-teresa-sullivan-ouster-_n_1619261.html",
          "display_url": "huffingtonpost.com/2012/06/24/uva…",
          "indices": [
            115,
            135
          ]
        }
      ],
      "user_mentions": [
        {
          "screen_name": "zachdcarter",
          "name": "Zach Carter",
          "id": 17119688,
          "id_str": "17119688",
          "indices": [
            44,
            56
          ]
        },
        {
          "screen_name": "dceiver",
          "name": "Jason Linkins",
          "id": 14066024,
          "id_str": "14066024",
          "indices": [
            63,
            71
          ]
        },
        {
          "screen_name": "HuffingtonPost",
          "name": "Huffington Post",
          "id": 14511951,
          "id_str": "14511951",
          "indices": [
            88,
            103
          ]
        }
      ]
    },
    "favorited": false,
    "retweeted": false,
    "possibly_sensitive": false
  },
  "retweet_count": 1,
  "entities": {
    "hashtags": [
      {
        "text": "UVA",
        "indices": [
          36,
          40
        ]
      },
      {
        "text": "Sullivan",
        "indices": [
          41,
          50
        ]
      }
    ],
    "urls": [

    ],
    "user_mentions": [
      {
        "screen_name": "johnruscher",
        "name": "John Ruscher",
        "id": 16024313,
        "id_str": "16024313",
        "indices": [
          3,
          15
        ]
      },
      {
        "screen_name": "zachdcarter",
        "name": "Zach Carter",
        "id": 17119688,
        "id_str": "17119688",
        "indices": [
          61,
          73
        ]
      },
      {
        "screen_name": "dceiver",
        "name": "Jason Linkins",
        "id": 14066024,
        "id_str": "14066024",
        "indices": [
          80,
          88
        ]
      },
      {
        "screen_name": "HuffingtonPost",
        "name": "Huffington Post",
        "id": 14511951,
        "id_str": "14511951",
        "indices": [
          105,
          120
        ]
      }
    ]
  },
  "favorited": false,
  "retweeted": false
}