{
  "created_at": "Tue Jun 26 19:47:49 +0000 2012",
  "id": 217705746362667008,
  "id_str": "217705746362667008",
  "text": "RT @cvillenewscom: This audience is rapt—rooted in place, silent except for bursts of applause. #UVA #BOV",
  "source": "<a href=\"http://tapbots.com/tweetbot\" rel=\"nofollow\">Tweetbot for iOS</a>",
  "truncated": false,
  "in_reply_to_status_id": null,
  "in_reply_to_status_id_str": null,
  "in_reply_to_user_id": null,
  "in_reply_to_user_id_str": null,
  "in_reply_to_screen_name": null,
  "user": {
    "id": 616427791,
    "id_str": "616427791",
    "name": "Rally For Honor 6/24",
    "screen_name": "RallyForHonor",
    "location": "Charlottesville, VA",
    "description": "Sunday 6/24, 2pm-4pm — Students, Faculty, Staff, Alums, Friends and Family will gather once again on the Lawn. http://t.co/jZsiDxs7",
    "url": "https://www.facebook.com/events/407375069312573/",
    "entities": {
      "url": {
        "urls": [
          {
            "url": "https://www.facebook.com/events/407375069312573/",
            "expanded_url": null,
            "indices": [
              0,
              48
            ]
          }
        ]
      },
      "description": {
        "urls": [
          {
            "url": "http://t.co/jZsiDxs7",
            "expanded_url": "http://ustre.am/LR8Z",
            "display_url": "ustre.am/LR8Z",
            "indices": [
              111,
              131
            ]
          }
        ]
      }
    },
    "protected": false,
    "followers_count": 17,
    "friends_count": 15,
    "listed_count": 0,
    "created_at": "Sat Jun 23 20:03:57 +0000 2012",
    "favourites_count": 49,
    "utc_offset": -14400,
    "time_zone": "Atlantic Time (Canada)",
    "geo_enabled": true,
    "verified": false,
    "statuses_count": 75,
    "lang": "en",
    "contributors_enabled": false,
    "is_translator": false,
    "profile_background_color": "C0DEED",
    "profile_background_image_url": "http://a0.twimg.com/profile_background_images/586644341/qhb0x0s7n9v2a649a2vo.png",
    "profile_background_image_url_https": "https://si0.twimg.com/profile_background_images/586644341/qhb0x0s7n9v2a649a2vo.png",
    "profile_background_tile": true,
    "profile_image_url": "http://a0.twimg.com/profile_images/2334537426/qe7fsxpu66g8tizctccl_normal.jpeg",
    "profile_image_url_https": "https://si0.twimg.com/profile_images/2334537426/qe7fsxpu66g8tizctccl_normal.jpeg",
    "profile_link_color": "0084B4",
    "profile_sidebar_border_color": "C0DEED",
    "profile_sidebar_fill_color": "DDEEF6",
    "profile_text_color": "333333",
    "profile_use_background_image": true,
    "default_profile": false,
    "default_profile_image": false,
    "following": false,
    "follow_request_sent": false,
    "notifications": false
  },
  "geo": null,
  "coordinates": null,
  "place": null,
  "contributors": null,
  "retweeted_status": {
    "created_at": "Tue Jun 26 19:44:25 +0000 2012",
    "id": 217704891886469120,
    "id_str": "217704891886469120",
    "text": "This audience is rapt—rooted in place, silent except for bursts of applause. #UVA #BOV",
    "source": "<a href=\"http://tapbots.com/tweetbot\" rel=\"nofollow\">Tweetbot for iOS</a>",
    "truncated": false,
    "in_reply_to_status_id": null,
    "in_reply_to_status_id_str": null,
    "in_reply_to_user_id": null,
    "in_reply_to_user_id_str": null,
    "in_reply_to_screen_name": null,
    "user": {
      "id": 52553230,
      "id_str": "52553230",
      "name": "cvillenews.com",
      "screen_name": "cvillenewscom",
      "location": "Charlottesville, VA",
      "description": "Charlottesville news tweetage. Maintained by @waldojaquith.",
      "url": "http://www.cvillenews.com/",
      "entities": {
        "url": {
          "urls": [
            {
              "url": "http://www.cvillenews.com/",
              "expanded_url": null,
              "indices": [
                0,
                26
              ]
            }
          ]
        },
        "description": {
          "urls": [

          ]
        }
      },
      "protected": false,
      "followers_count": 1166,
      "friends_count": 17,
      "listed_count": 79,
      "created_at": "Tue Jun 30 23:04:41 +0000 2009",
      "favourites_count": 32,
      "utc_offset": -18000,
      "time_zone": "Eastern Time (US & Canada)",
      "geo_enabled": true,
      "verified": false,
      "statuses_count": 1385,
      "lang": "en",
      "contributors_enabled": false,
      "is_translator": false,
      "profile_background_color": "C0DEED",
      "profile_background_image_url": "http://a0.twimg.com/images/themes/theme1/bg.png",
      "profile_background_image_url_https": "https://si0.twimg.com/images/themes/theme1/bg.png",
      "profile_background_tile": false,
      "profile_image_url": "http://a0.twimg.com/profile_images/291110792/waldo_normal.png",
      "profile_image_url_https": "https://si0.twimg.com/profile_images/291110792/waldo_normal.png",
      "profile_link_color": "0084B4",
      "profile_sidebar_border_color": "C0DEED",
      "profile_sidebar_fill_color": "DDEEF6",
      "profile_text_color": "333333",
      "profile_use_background_image": true,
      "default_profile": true,
      "default_profile_image": false,
      "following": true,
      "follow_request_sent": false,
      "notifications": null
    },
    "geo": null,
    "coordinates": null,
    "place": null,
    "contributors": null,
    "retweet_count": 3,
    "entities": {
      "hashtags": [
        {
          "text": "UVA",
          "indices": [
            77,
            81
          ]
        },
        {
          "text": "BOV",
          "indices": [
            82,
            86
          ]
        }
      ],
      "urls": [

      ],
      "user_mentions": [

      ]
    },
    "favorited": false,
    "retweeted": false
  },
  "retweet_count": 3,
  "entities": {
    "hashtags": [
      {
        "text": "UVA",
        "indices": [
          96,
          100
        ]
      },
      {
        "text": "BOV",
        "indices": [
          101,
          105
        ]
      }
    ],
    "urls": [

    ],
    "user_mentions": [
      {
        "screen_name": "cvillenewscom",
        "name": "cvillenews.com",
        "id": 52553230,
        "id_str": "52553230",
        "indices": [
          3,
          17
        ]
      }
    ]
  },
  "favorited": false,
  "retweeted": false
}