{
  "created_at": "Fri Jun 29 02:53:37 +0000 2012",
  "id": 218537678638026752,
  "id_str": "218537678638026752",
  "text": "RT @qui_oui: New @UVenus post: at #UVa, trouble with transparency &amp; governance http://t.co/mcOzW83S #highered",
  "source": "<a href=\"http://www.nibirutech.com/\" rel=\"nofollow\">TwitBird iPad</a>",
  "truncated": false,
  "in_reply_to_status_id": null,
  "in_reply_to_status_id_str": null,
  "in_reply_to_user_id": null,
  "in_reply_to_user_id_str": null,
  "in_reply_to_screen_name": null,
  "user": {
    "id": 74021073,
    "id_str": "74021073",
    "name": "Miguel Angel Escotet",
    "screen_name": "DrEscotet",
    "location": "Texas",
    "description": "Dean, College of Education, University of Texas at Brownsville. Psychologist, Philosopher, Researcher and Int'l HigherEd. Tweets are my own personal perspective",
    "url": "http://www.miguelescotet.com",
    "entities": {
      "url": {
        "urls": [
          {
            "url": "http://www.miguelescotet.com",
            "expanded_url": null,
            "indices": [
              0,
              28
            ]
          }
        ]
      },
      "description": {
        "urls": [

        ]
      }
    },
    "protected": false,
    "followers_count": 16992,
    "friends_count": 502,
    "listed_count": 232,
    "created_at": "Mon Sep 14 00:58:43 +0000 2009",
    "favourites_count": 127,
    "utc_offset": -21600,
    "time_zone": "Central Time (US & Canada)",
    "geo_enabled": false,
    "verified": false,
    "statuses_count": 29689,
    "lang": "en",
    "contributors_enabled": false,
    "is_translator": false,
    "profile_background_color": "FFFFFF",
    "profile_background_image_url": "http://a0.twimg.com/profile_background_images/206741897/twilk_background_4d5dacb386548.jpg",
    "profile_background_image_url_https": "https://si0.twimg.com/profile_background_images/206741897/twilk_background_4d5dacb386548.jpg",
    "profile_background_tile": false,
    "profile_image_url": "http://a0.twimg.com/profile_images/1435826315/Esc11_normal.jpg",
    "profile_image_url_https": "https://si0.twimg.com/profile_images/1435826315/Esc11_normal.jpg",
    "profile_link_color": "8CB2BD",
    "profile_sidebar_border_color": "8CB2BD",
    "profile_sidebar_fill_color": "424C55",
    "profile_text_color": "8C94A2",
    "profile_use_background_image": true,
    "default_profile": false,
    "default_profile_image": false,
    "following": false,
    "follow_request_sent": false,
    "notifications": false
  },
  "geo": null,
  "coordinates": null,
  "place": null,
  "contributors": null,
  "retweeted_status": {
    "created_at": "Fri Jun 29 02:43:34 +0000 2012",
    "id": 218535150227685376,
    "id_str": "218535150227685376",
    "text": "New @UVenus post: at #UVa, trouble with transparency &amp; governance http://t.co/mcOzW83S #highered",
    "source": "<a href=\"http://www.tweetdeck.com\" rel=\"nofollow\">TweetDeck</a>",
    "truncated": false,
    "in_reply_to_status_id": null,
    "in_reply_to_status_id_str": null,
    "in_reply_to_user_id": null,
    "in_reply_to_user_id_str": null,
    "in_reply_to_screen_name": null,
    "user": {
      "id": 15053275,
      "id_str": "15053275",
      "name": "Melonie Fullick",
      "screen_name": "qui_oui",
      "location": "Hamilton",
      "description": "Education, blogging, politics, communication. Working on a PhD in Post-Secondary Ed policy, governance & theory. I also like cats & photos. Kiwinadian.",
      "url": "http://www.universityaffairs.ca/speculative-diction/",
      "entities": {
        "url": {
          "urls": [
            {
              "url": "http://www.universityaffairs.ca/speculative-diction/",
              "expanded_url": null,
              "indices": [
                0,
                52
              ]
            }
          ]
        },
        "description": {
          "urls": [

          ]
        }
      },
      "protected": false,
      "followers_count": 2399,
      "friends_count": 949,
      "listed_count": 216,
      "created_at": "Mon Jun 09 03:18:29 +0000 2008",
      "favourites_count": 555,
      "utc_offset": -18000,
      "time_zone": "Eastern Time (US & Canada)",
      "geo_enabled": false,
      "verified": false,
      "statuses_count": 49335,
      "lang": "en",
      "contributors_enabled": false,
      "is_translator": false,
      "profile_background_color": "1A1B1F",
      "profile_background_image_url": "http://a0.twimg.com/profile_background_images/492073122/DSC01540_Field_Novaresco___4_.jpg",
      "profile_background_image_url_https": "https://si0.twimg.com/profile_background_images/492073122/DSC01540_Field_Novaresco___4_.jpg",
      "profile_background_tile": false,
      "profile_image_url": "http://a0.twimg.com/profile_images/2546785281/av6rvada6c2l0k583864_normal.jpeg",
      "profile_image_url_https": "https://si0.twimg.com/profile_images/2546785281/av6rvada6c2l0k583864_normal.jpeg",
      "profile_banner_url": "https://si0.twimg.com/profile_banners/15053275/1358370222",
      "profile_link_color": "EDA72F",
      "profile_sidebar_border_color": "181A1E",
      "profile_sidebar_fill_color": "252429",
      "profile_text_color": "666666",
      "profile_use_background_image": true,
      "default_profile": false,
      "default_profile_image": false,
      "following": false,
      "follow_request_sent": false,
      "notifications": false
    },
    "geo": null,
    "coordinates": null,
    "place": null,
    "contributors": null,
    "retweet_count": 4,
    "entities": {
      "hashtags": [
        {
          "text": "UVa",
          "indices": [
            21,
            25
          ]
        },
        {
          "text": "highered",
          "indices": [
            91,
            100
          ]
        }
      ],
      "urls": [
        {
          "url": "http://t.co/mcOzW83S",
          "expanded_url": "http://bit.ly/LUtiZd",
          "display_url": "bit.ly/LUtiZd",
          "indices": [
            70,
            90
          ]
        }
      ],
      "user_mentions": [
        {
          "screen_name": "UVenus",
          "name": "University of Venus",
          "id": 100986108,
          "id_str": "100986108",
          "indices": [
            4,
            11
          ]
        }
      ]
    },
    "favorited": false,
    "retweeted": false,
    "possibly_sensitive": false
  },
  "retweet_count": 4,
  "entities": {
    "hashtags": [
      {
        "text": "UVa",
        "indices": [
          34,
          38
        ]
      },
      {
        "text": "highered",
        "indices": [
          104,
          113
        ]
      }
    ],
    "urls": [
      {
        "url": "http://t.co/mcOzW83S",
        "expanded_url": "http://bit.ly/LUtiZd",
        "display_url": "bit.ly/LUtiZd",
        "indices": [
          83,
          103
        ]
      }
    ],
    "user_mentions": [
      {
        "screen_name": "qui_oui",
        "name": "Melonie Fullick",
        "id": 15053275,
        "id_str": "15053275",
        "indices": [
          3,
          11
        ]
      },
      {
        "screen_name": "UVenus",
        "name": "University of Venus",
        "id": 100986108,
        "id_str": "100986108",
        "indices": [
          17,
          24
        ]
      }
    ]
  },
  "favorited": false,
  "retweeted": false,
  "possibly_sensitive": false
}