{
  "created_at": "Tue Jul 03 19:53:01 +0000 2012",
  "id": 220243771609198592,
  "id_str": "220243771609198592",
  "text": "I'm such a tomboy #bov",
  "source": "<a href=\"http://twitter.com/download/iphone\" rel=\"nofollow\">Twitter for iPhone</a>",
  "truncated": false,
  "in_reply_to_status_id": null,
  "in_reply_to_status_id_str": null,
  "in_reply_to_user_id": null,
  "in_reply_to_user_id_str": null,
  "in_reply_to_screen_name": null,
  "user": {
    "id": 420519543,
    "id_str": "420519543",
    "name": "chlo xx",
    "screen_name": "MerryChloe",
    "location": "Cambridge",
    "description": "x3 ",
    "url": null,
    "entities": {
      "description": {
        "urls": [

        ]
      }
    },
    "protected": false,
    "followers_count": 331,
    "friends_count": 297,
    "listed_count": 1,
    "created_at": "Thu Nov 24 18:51:29 +0000 2011",
    "favourites_count": 504,
    "utc_offset": null,
    "time_zone": null,
    "geo_enabled": true,
    "verified": false,
    "statuses_count": 6273,
    "lang": "en",
    "contributors_enabled": false,
    "is_translator": false,
    "profile_background_color": "C0DEED",
    "profile_background_image_url": "http://a0.twimg.com/images/themes/theme1/bg.png",
    "profile_background_image_url_https": "https://si0.twimg.com/images/themes/theme1/bg.png",
    "profile_background_tile": false,
    "profile_image_url": "http://a0.twimg.com/profile_images/3182912872/3d7ddcd6ead466b78b67c2ff86a957a3_normal.jpeg",
    "profile_image_url_https": "https://si0.twimg.com/profile_images/3182912872/3d7ddcd6ead466b78b67c2ff86a957a3_normal.jpeg",
    "profile_banner_url": "https://si0.twimg.com/profile_banners/420519543/1358507166",
    "profile_link_color": "0084B4",
    "profile_sidebar_border_color": "C0DEED",
    "profile_sidebar_fill_color": "DDEEF6",
    "profile_text_color": "333333",
    "profile_use_background_image": true,
    "default_profile": true,
    "default_profile_image": false,
    "following": false,
    "follow_request_sent": false,
    "notifications": false
  },
  "geo": null,
  "coordinates": null,
  "place": null,
  "contributors": null,
  "retweet_count": 0,
  "entities": {
    "hashtags": [
      {
        "text": "bov",
        "indices": [
          18,
          22
        ]
      }
    ],
    "urls": [

    ],
    "user_mentions": [

    ]
  },
  "favorited": false,
  "retweeted": false
}